scrunch/__init__.py
scrunch/accounts.py
scrunch/categories.py
scrunch/connections.py
scrunch/crunchboxes.py
scrunch/cubes.py
scrunch/datasets.py
scrunch/exceptions.py
scrunch/expressions.py
scrunch/folders.py
scrunch/helpers.py
scrunch/mutable_dataset.py
scrunch/order.py
scrunch/scripts.py
scrunch/session.py
scrunch/streaming_dataset.py
scrunch/subentity.py
scrunch/variables.py
scrunch/version.py
scrunch/views.py
scrunch/tests/__init__.py
scrunch/tests/crunch_test.ini
scrunch/tests/crunch_test_api_key.ini
scrunch/tests/mock_session.py
scrunch/tests/test_accounts.py
scrunch/tests/test_categories.py
scrunch/tests/test_cubes.py
scrunch/tests/test_datasets.py
scrunch/tests/test_expressions.py
scrunch/tests/test_folders.py
scrunch/tests/test_projects.py
scrunch/tests/test_recodes.py
scrunch/tests/test_scripts.py
scrunch/tests/test_teams.py
scrunch/tests/test_utilities.py
scrunch/tests/test_views.py
scrunch/tests/integration/scrunch_workflow_integration_test.py
scrunch-1692282992.dist-info/LICENSE
scrunch-1692282992.dist-info/METADATA
scrunch-1692282992.dist-info/WHEEL
scrunch-1692282992.dist-info/namespace_packages.txt
scrunch-1692282992.dist-info/top_level.txt
scrunch-1692282992.dist-info/RECORD
