Metadata-Version: 2.1
Name: scrunch
Version: 1692282992
Summary: Pythonic scripting library for cleaning data in Crunch
Home-page: https://github.com/Crunch-io/scrunch
Author: Crunch.io
Author-email: dev@crunch.io
License: UNKNOWN
Platform: UNKNOWN
Classifier: Development Status :: 5 - Production/Stable
Classifier: Intended Audience :: Developers
Classifier: License :: OSI Approved :: GNU Lesser General Public License v3 (LGPLv3)
Classifier: Programming Language :: Python :: 2.7
Classifier: Programming Language :: Python :: 3
Requires-Python: >=2.7
Requires-Dist: pycrunch ==0.5.5
Requires-Dist: requests ==2.27.0
Requires-Dist: cr.cube
Requires-Dist: six
Provides-Extra: docs
Requires-Dist: sphinx ; extra == 'docs'
Requires-Dist: jaraco.packaging >=3.2 ; extra == 'docs'
Requires-Dist: rst.linker >=1.9 ; extra == 'docs'
Provides-Extra: pandas
Requires-Dist: pandas ; extra == 'pandas'
Provides-Extra: testing
Requires-Dist: pytest ==4.6.11 ; extra == 'testing'
Requires-Dist: collective.checkdocs ; extra == 'testing'
Requires-Dist: pytest-cov ==2.12.1 ; extra == 'testing'
Requires-Dist: mock ==3.0.5 ; extra == 'testing'
Requires-Dist: isodate ; extra == 'testing'
Requires-Dist: backports.unittest-mock ; extra == 'testing'
